fpga/rtl/core/alu_ctrl.vhd
library IEEE;
use IEEE.std_logic_1164.all;

entity alu_ctrl is
  port(
    alu_op      : in  std_logic_vector(1 downto 0);
    func_code   : in  std_logic_vector(5 downto 0);
    alu_control : out std_logic_vector(3 downto 0)
    );
end alu_ctrl;

architecture env_alu_ctrl of alu_ctrl is
begin
  process_alu_ctrl : process(alu_op, func_code)
  begin
    case alu_op(1 downto 0) is
      when "00" => alu_control <= "0010";          --add
      when "01" => alu_control <= "0110";          --subs
      when "10" =>
        case func_code(5 downto 0) is
          when "100000" => alu_control <= "0010";  --add
          when "100010" => alu_control <= "0110";  --subs
          when "100100" => alu_control <= "0000";  --and
          when "100101" => alu_control <= "0001";  --or
          when "100111" => alu_control <= "1100";  --nor
          when "101010" => alu_control <= "0111";  --slt
          when others   => alu_control <= "1111";
        end case;
      when others => alu_control <= "1111";
    end case;
  end process process_alu_ctrl;
end env_alu_ctrl;

fpga/tb/alu_ctrl_tb.vhd
library IEEE;
use IEEE.std_logic_1164.all;

entity alu_ctrl_tb is
end alu_ctrl_tb;

architecture alu_ctrl_tb_arch of alu_ctrl_tb is
  component alu_ctrl
    port(
      alu_op      : in  std_logic_vector(1 downto 0);
      func_code   : in  std_logic_vector(5 downto 0);
      alu_control : out std_logic_vector(3 downto 0)
      );
  end component;

  signal alu_op      : std_logic_vector (1 downto 0) := "00";
  signal func_code   : std_logic_vector (5 downto 0) := "000000";
  signal alu_control : std_logic_vector(3 downto 0);

begin
  UUT : alu_ctrl
    port map(
      alu_op      => alu_op,
      func_code   => func_code,
      alu_control => alu_control
      );

  alu_op    <= "01"     after 10 ns, "10" after 20 ns;
  func_code <= "100000" after 20 ns, "100010" after 30 ns, "100100" after 40 ns, "100101" after 50 ns, "100111" after 60 ns, "101010" after 70 ns, "111111" after 80 ns;
end alu_ctrl_tb_arch;

fpga/tb/alu_ctrl_waves.vcd
$date
	Fri Mar 27 17:55:42 2026
$end
$version
	ModelSim Version 2020.1
$end
$timescale
	1ps
$end

$scope module alu_ctrl_tb $end
$var wire 1 ! alu_op [1] $end
$var wire 1 " alu_op [0] $end
$var wire 1 # func_code [5] $end
$var wire 1 $ func_code [4] $end
$var wire 1 % func_code [3] $end
$var wire 1 & func_code [2] $end
$var wire 1 ' func_code [1] $end
$var wire 1 ( func_code [0] $end
$var wire 1 ) alu_control [3] $end
$var wire 1 * alu_control [2] $end
$var wire 1 + alu_control [1] $end
$var wire 1 , alu_control [0] $end

$scope module UUT $end
$var wire 1 ! alu_op [1] $end
$var wire 1 " alu_op [0] $end
$var wire 1 # func_code [5] $end
$var wire 1 $ func_code [4] $end
$var wire 1 % func_code [3] $end
$var wire 1 & func_code [2] $end
$var wire 1 ' func_code [1] $end
$var wire 1 ( func_code [0] $end
$var wire 1 ) alu_control [3] $end
$var wire 1 * alu_control [2] $end
$var wire 1 + alu_control [1] $end
$var wire 1 , alu_control [0] $end
$upscope $end
$upscope $end
$enddefinitions $end
#0
$dumpvars
0!
0"
0#
0$
0%
0&
0'
0(
0)
0*
1+
0,
$end
#10000
1"
1*
#20000
1#
1!
0"
0*
#30000
1'
1*
#40000
1&
0'
0+
0*
#50000
1(
1,
#60000
1'
0,
1*
1)
#70000
1%
0(
0&
1,
1+
0)
#80000
1$
1&
1(
1)
